public_sort/__init__.py
public_sort/public_sort.py
publicsort-1.0.0.dist-info/LICENSE
publicsort-1.0.0.dist-info/METADATA
publicsort-1.0.0.dist-info/WHEEL
publicsort-1.0.0.dist-info/entry_points.txt
publicsort-1.0.0.dist-info/top_level.txt
publicsort-1.0.0.dist-info/RECORD
