Metadata-Version: 2.1
Name: publicsort
Version: 1.0.0
Summary: ('public.xml排序',)
Home-page: https://github.com/pypa/sampleproject
Author: XiaoTian
Author-email: 1961993790@qq.com
Classifier: Programming Language :: Python :: 3
Classifier: License :: OSI Approved :: MIT License
Classifier: Operating System :: OS Independent
License-File: LICENSE
